nut_report/__init__.py
nut_report/cli.py
nut_report/nut_report.py
nut_report-1.0.0.dist-info/LICENSE
nut_report-1.0.0.dist-info/METADATA
nut_report-1.0.0.dist-info/WHEEL
nut_report-1.0.0.dist-info/entry_points.txt
nut_report-1.0.0.dist-info/top_level.txt
nut_report-1.0.0.dist-info/RECORD
