Metadata-Version: 2.1
Name: nut_report
Version: 1.0.0
Summary: Demo parser utility for Counter-Strike 2
Author-email: WTFender <wtfender.cs@gmail.com>
Project-URL: Homepage, https://github.com/WTFender/nut_report
Project-URL: Issues, https://github.com/WTFender/nut_report/issues
Classifier: Programming Language :: Python :: 3
Classifier: License :: OSI Approved :: MIT License
Classifier: Operating System :: OS Independent
Requires-Python: >=3.8
License-File: LICENSE
Requires-Dist: console-menu >=0.8.0
Requires-Dist: demoparser2 >=0.28.0
Requires-Dist: numpy >=2.0.1
Requires-Dist: pandas >=2.2.2
Requires-Dist: prettytable >=3.10.2
Requires-Dist: python-dotenv >=1.0.1
Requires-Dist: requests >=2.32.3
